{
  "id": "journey_1",
  "background": "backgrounds/bg_street_1.png",
  "characters": [],
  "dialogue": [
    { "speaker": "", "text": "(И снова эта липкая жара. Вокзал не так уж и далеко... но как будто всё тело против.)" },
    { "speaker": "", "text": "(Раньше мы с девчонками носились по городу до темноты, как будто нам всё можно было.)" },
    { "speaker": "", "text": "(А теперь — в их сторис только парни и кафешки. Меня даже не спрашивают, жива ли я.)" }
  ],
  "choices": [
    { "text": "Продолжить", "next_scene": "journey_2" }
  ]
}
